ppam/__init__.py
ppam/cli.py
ppam/config.py
ppam/utils.py
ppam-0.1.0.dist-info/LICENSE
ppam-0.1.0.dist-info/METADATA
ppam-0.1.0.dist-info/WHEEL
ppam-0.1.0.dist-info/entry_points.txt
ppam-0.1.0.dist-info/top_level.txt
ppam-0.1.0.dist-info/RECORD
