Metadata-Version: 2.1
Name: ppam
Version: 0.1.0
Summary: pip wrapper that auto-updates requirements.txt
Home-page: UNKNOWN
Author: Umesh Kumar Bedi
License: MIT
Platform: UNKNOWN
Requires-Python: >=3.7
